Metadata-Version: 1.1
Name: wsl-path-exe
Version: 0.0.1
Summary: UNKNOWN
Home-page: https://github.com/gutierri/wsl-path-exe
Author: Gutierri Barbiza
Author-email: me@gutierri.me
License: UNKNOWN
Platform: UNKNOWN
Classifier: Development Status :: 3 - Alpha
